barim/__init__.py
barim/abstracts.py
barim/ansi.py
barim/base.py
barim/decorators.py
barim/exceptions.py
barim/utils.py
barim-0.1.1.dist-info/LICENSE
barim-0.1.1.dist-info/WHEEL
barim-0.1.1.dist-info/METADATA
barim-0.1.1.dist-info/RECORD
